{
  "main": {
    "id": "b9605f8964eda04f",
    "type": "split",
    "children": [
      {
        "id": "05eaaa75a28d9b3a",
        "type": "tabs",
        "children": [
          {
            "id": "1dfa773e98d4d1f3",
            "type": "leaf",
            "state": {
              "type": "markdown",
              "state": {
                "file": "WebComics/Script/Volume 1 - Strange matters.md",
                "mode": "source",
                "source": false
              },
              "icon": "lucide-file",
              "title": "Volume 1 - Strange matters"
            }
          }
        ]
      }
    ],
    "direction": "vertical"
  },
  "left": {
    "id": "863247237a219031",
    "type": "split",
    "children": [
      {
        "id": "935831bf721fbd79",
        "type": "tabs",
        "children": [
          {
            "id": "333f9fca556a56b7",
            "type": "leaf",
            "state": {
              "type": "file-explorer",
              "state": {
                "sortOrder": "alphabetical",
                "autoReveal": false
              },
              "icon": "lucide-folder-closed",
              "title": "Files"
            }
          },
          {
            "id": "5d948b610e9ffd19",
            "type": "leaf",
            "state": {
              "type": "search",
              "state": {
                "query": "",
                "matchingCase": false,
                "explainSearch": false,
                "collapseAll": false,
                "extraContext": false,
                "sortOrder": "alphabetical"
              },
              "icon": "lucide-search",
              "title": "Search"
            }
          },
          {
            "id": "68135ddbbffabfdf",
            "type": "leaf",
            "state": {
              "type": "bookmarks",
              "state": {},
              "icon": "lucide-bookmark",
              "title": "Bookmarks"
            }
          }
        ]
      }
    ],
    "direction": "horizontal",
    "width": 200
  },
  "right": {
    "id": "2d169052be288754",
    "type": "split",
    "children": [
      {
        "id": "46ec57043cee0e91",
        "type": "tabs",
        "children": [
          {
            "id": "c3a4e3fdab935910",
            "type": "leaf",
            "state": {
              "type": "backlink",
              "state": {
                "file": "SSR.md",
                "collapseAll": false,
                "extraContext": false,
                "sortOrder": "alphabetical",
                "showSearch": false,
                "searchQuery": "",
                "backlinkCollapsed": false,
                "unlinkedCollapsed": true
              },
              "icon": "links-coming-in",
              "title": "Backlinks for SSR"
            }
          },
          {
            "id": "58d62655aa039a74",
            "type": "leaf",
            "state": {
              "type": "outgoing-link",
              "state": {
                "file": "SSR.md",
                "linksCollapsed": false,
                "unlinkedCollapsed": true
              },
              "icon": "links-going-out",
              "title": "Outgoing links from SSR"
            }
          },
          {
            "id": "13aee147690f069a",
            "type": "leaf",
            "state": {
              "type": "tag",
              "state": {
                "sortOrder": "frequency",
                "useHierarchy": true,
                "showSearch": false,
                "searchQuery": ""
              },
              "icon": "lucide-tags",
              "title": "Tags"
            }
          },
          {
            "id": "b219a4e2a06b06ca",
            "type": "leaf",
            "state": {
              "type": "outline",
              "state": {
                "file": "SSR.md",
                "followCursor": false,
                "showSearch": false,
                "searchQuery": ""
              },
              "icon": "lucide-list",
              "title": "Outline of SSR"
            }
          }
        ]
      }
    ],
    "direction": "horizontal",
    "width": 300,
    "collapsed": true
  },
  "left-ribbon": {
    "hiddenItems": {
      "bases:Create new base": false,
      "switcher:Open quick switcher": false,
      "graph:Open graph view": false,
      "canvas:Create new canvas": false,
      "daily-notes:Open today's daily note": false,
      "templates:Insert template": false,
      "command-palette:Open command palette": false,
      "templater-obsidian:Templater": false
    }
  },
  "active": "1dfa773e98d4d1f3",
  "lastOpenFiles": [
    "Tests D'acceptance EspaceClient Novatrans.md",
    "WebComics/Script/Volume 1 - Strange matters.md",
    "Expliquation methode extractUniqueCategoriesFromResults().md",
    "README.md",
    "Alternance/MissionsSupp/Point à voir dans l'avenir proche.md",
    "Untitled.base",
    "Nouveaux sujets.md",
    "Alternance/MissionsSupp/Untitled.md",
    "comment fonctionne le test de playwright.md",
    "Alternance/OTC Novatrans EspaceClient/Analyse du projet OTC Novatrans Espace Client.md",
    "Alternance/OTC Novatrans EspaceClient",
    "Alternance/MissionsSupp/Plan pour la présentation.md",
    "Alternance/MissionsSupp/Intégrer Playwright à Dashboard.md",
    "GameDev/Black Bismuth/Lore/Lore, Old Version (UKR).md",
    "GameDev/game elements table.md",
    "GameDev/Rogue-like Dark Fantasy Structure.md",
    "WebComics/Lore/Narration.md",
    "Comics Univers/Black Bismuth Lore.md",
    "Vrac/Inspiration 1.md",
    "WebComics/Lore/Dossier Delta-09 Torpedo.md",
    "Vrac/CV notes.md",
    "WebComics/Lore/Деф’янс 1 Створення нових героїв.md",
    "WebComics/Lore/Ендрю Марш - Суперсолдат.md",
    "WebComics/Lore/Список додаткових персонажів коміксів.md",
    "Alternance/Soutenance/Presentation de Soutenance d'alternance.md",
    "WebComics/Lore/Untitled",
    "WebComics/Lore/Contexte historique de Paul Mercer.md",
    "Alternance/Soutenance/Script de la présentation.md",
    "WebComics/Script",
    "Vrac/période fin 2025.md",
    "GameDev/Projet de jeu 48heures",
    "WebComics/Lore/WebComics.canvas",
    "GameDev/Black Bismuth/Hack&Slash Logic.canvas",
    "GameDev/Black Bismuth/Images",
    "Comics Univers/Untitled.canvas",
    "GameDev/Black Bismuth/Lore/Hesperedia 6.png",
    "GameDev/Black Bismuth/Lore/Hesperedia.png",
    "Comics Univers/AetherMap.jpg",
    "Alternance/Images/Carte Europe GCA.png",
    "Alternance/Soutenance",
    "Alternance/Images/diagrame de classe gca-argocd-api.png",
    "Comics Univers",
    "Alternance/Images/Core_Concepts_Keycloak.webp",
    "Alternance/MissionsSupp",
    "Alternance/FormationTechno"
  ]
}